setup.py
sackeylib/SDF_Struck_lib.py
sackeylib/__init__.py
sackeylib/sackey_lib.py
sackeylib.egg-info/PKG-INFO
sackeylib.egg-info/SOURCES.txt
sackeylib.egg-info/dependency_links.txt
sackeylib.egg-info/top_level.txt