Metadata-Version: 2.1
Name: sackeylib
Version: 0.0.26
Summary: ...
Home-page: https://github.com/Sackey-yuan/nvm
Author: Yuanshaohua
Author-email: 739115136@qq.com
Classifier: Programming Language :: Python :: 3
Classifier: License :: OSI Approved :: MIT License
Classifier: Operating System :: OS Independent
